edocuments/__init__.py
edocuments/backend.py
edocuments/index.py
edocuments/label_dialog.py
edocuments/main_widget.py
edocuments/ressources/config.yaml
edocuments/ressources/edocuments.desktop
edocuments/ressources/edocuments.png
edocuments/ressources/edocuments.svg
edocuments/ui/__init__.py
edocuments/ui/label_dialog.py
edocuments/ui/main.py
edocuments-1.1.0.dist-info/DESCRIPTION.rst
edocuments-1.1.0.dist-info/METADATA
edocuments-1.1.0.dist-info/RECORD
edocuments-1.1.0.dist-info/WHEEL
edocuments-1.1.0.dist-info/entry_points.txt
edocuments-1.1.0.dist-info/metadata.json
edocuments-1.1.0.dist-info/top_level.txt
