Metadata-Version: 2.0
Name: edocuments
Version: 1.1.0
Summary: eDocuments - a simple and productive personal documents library
Home-page: https://github.com/sbrunner/edocuments/
Author: Stéphane Brunner
Author-email: stephane.brunner@gmail.com
License: UNKNOWN
Keywords: simple productive personal documents library scan index search
Platform: UNKNOWN
Classifier: Programming Language :: Python :: 3
Requires-Dist: Mako
Requires-Dist: PyYAML
Requires-Dist: Whoosh
Requires-Dist: bashcolor (>=1.0.0)
Requires-Dist: bottle
Requires-Dist: metatask (>=1.0.0)
